VNSFintech/__init__.py
VNSFintech/finance.py
VNSFintech/fund.py
VNSFintech/holder.py
VNSFintech/macro_eco.py
VNSFintech/stock.py
VNSFintech/stocklist.py
vnsfintech-0.0.17.dist-info/licenses/LICENSE
vnsfintech-0.0.17.dist-info/METADATA
vnsfintech-0.0.17.dist-info/WHEEL
vnsfintech-0.0.17.dist-info/top_level.txt
vnsfintech-0.0.17.dist-info/RECORD
