Metadata-Version: 2.4
Name: VNSFintech
Version: 0.0.17
Summary: Thư viện cung cấp các công cụ mạnh mẽ và dữ liệu chi tiết hỗ trợ phân tích tài chính, thị trường chứng khoán
Author: Duc Minh
Author-email: luongbaoquan25@gmail.com
Requires-Python: >=3.7
License-File: LICENSE
Requires-Dist: requests
Requires-Dist: pandas
Dynamic: license-file
